{
    "fluentMethods": true,
    "relationships": [],
    "fields": [
        {
            "fieldName": "accountId",
            "fieldType": "Long"
        },
        {
            "fieldName": "moneyInvested",
            "fieldType": "Integer"
        },
        {
            "fieldName": "address",
            "fieldType": "String"
        }
    ],
    "changelogDate": "20170727174457",
    "dto": "no",
    "service": "serviceImpl",
    "entityTableName": "extended_user",
    "pagination": "no"
}
